jurebes/__init__.py
jurebes/version.py
jurebes-0.1.1.dist-info/METADATA
jurebes-0.1.1.dist-info/WHEEL
jurebes-0.1.1.dist-info/top_level.txt
jurebes-0.1.1.dist-info/zip-safe
jurebes-0.1.1.dist-info/RECORD
