Metadata-Version: 2.1
Name: jurebes
Version: 0.1.1
Summary: A intent parser from OpenVoiceOS
Home-page: https://github.com/OpenVoiceOS/jurebes
Author: JarbasAi
Author-email: jarbasai@mailfence.com
License: Apache-2.0
Platform: UNKNOWN
Classifier: Development Status :: 3 - Alpha
Classifier: Intended Audience :: Developers
Classifier: Topic :: Text Processing :: Linguistic
Classifier: License :: OSI Approved :: Apache Software License
Classifier: Programming Language :: Python :: 3.4
Classifier: Programming Language :: Python :: 3.5
Classifier: Programming Language :: Python :: 3.6
Requires-Dist: ovos-utils
Requires-Dist: ovos-classifiers[sklearn] (>=0.0.0a1)
Requires-Dist: padacioso
Requires-Dist: quebra-frases
Requires-Dist: nltk
